airflow_dagfactory/__init__.py
airflow_dagfactory/__version__.py
airflow_dagfactory/dagbuilder.py
airflow_dagfactory/dagfactory.py
airflow_dagfactory/exceptions.py
airflow_dagfactory/utils.py
airflow_dagfactory-0.19.2.dist-info/LICENSE
airflow_dagfactory-0.19.2.dist-info/METADATA
airflow_dagfactory-0.19.2.dist-info/WHEEL
airflow_dagfactory-0.19.2.dist-info/top_level.txt
airflow_dagfactory-0.19.2.dist-info/RECORD
