Metadata-Version: 2.1
Name: airflow-dagfactory
Version: 0.19.2
Summary: Dynamically build Airflow DAGs from YAML files
Home-page: https://github.com/quydx/dag-factory
Author: Quy Do
Author-email: quybulu@gmail.com
License: MIT
Keywords: airflow
Classifier: License :: OSI Approved :: MIT License
Classifier: Programming Language :: Python
Classifier: Programming Language :: Python :: 3
Classifier: Programming Language :: Python :: 3.10
Classifier: Programming Language :: Python :: Implementation :: CPython
Classifier: Programming Language :: Python :: Implementation :: PyPy
Requires-Python: >=3.10.0
License-File: LICENSE
Requires-Dist: apache-airflow[http,kubernetes] ==2.9.1
Requires-Dist: pyyaml
Requires-Dist: packaging
Requires-Dist: SQLAlchemy ==2.0.30
Provides-Extra: dev
Requires-Dist: black ; extra == 'dev'
Requires-Dist: pytest ; extra == 'dev'
Requires-Dist: pylint ; extra == 'dev'
Requires-Dist: pytest-cov ; extra == 'dev'
Requires-Dist: tox ; extra == 'dev'
